istalktrance/__init__.py
istalktrance/main.py
istalktrance-0.4.dist-info/METADATA
istalktrance-0.4.dist-info/WHEEL
istalktrance-0.4.dist-info/top_level.txt
istalktrance-0.4.dist-info/RECORD
