Metadata-Version: 2.1
Name: istalktrance
Version: 0.4
Requires-Dist: numpy>=1.11.1
